astro/__init__.py
astro/constants.py
astro/geodetic.py
astro/kepler.py
astro/kernels.py
astro/maneuver.py
astro/manuever.py
astro/planets.py
astro/predict.py
astro/propogator.py
astro/satellite.py
astro/time.py
astro/tle.py
astro/transform.py
astro/tests/__init__.py
astro/tests/test_constants.py
astro/tests/test_geodetic.py
astro/tests/test_kepler.py
astro/tests/test_kernels.py
astro/tests/test_manuever.py
astro/tests/test_planets.py
astro/tests/test_satellite.py
astro/tests/test_spiceypy.py
astro/tests/test_time.py
astro/tests/test_tle.py
astro/tests/test_transform.py
astro-0.1.8.data/scripts/predict.py
astro-0.1.8.data/scripts/tle.py
astro-0.1.8.dist-info/DESCRIPTION.rst
astro-0.1.8.dist-info/METADATA
astro-0.1.8.dist-info/RECORD
astro-0.1.8.dist-info/WHEEL
astro-0.1.8.dist-info/metadata.json
astro-0.1.8.dist-info/top_level.txt
